CacheLibrary/__init__.py
CacheLibrary/CacheLibrary.py
robotframework_cache-1.0.1.dist-info/LICENSE
robotframework_cache-1.0.1.dist-info/METADATA
robotframework_cache-1.0.1.dist-info/WHEEL
robotframework_cache-1.0.1.dist-info/RECORD
