Metadata-Version: 2.1
Name: robotframework-cache
Version: 1.0.1
Summary: Robot Framework libary for caching values across tests and test runs
License: MIT
Author: Sander van Beek
Author-email: lakitna@gmail.com
Requires-Python: >=3.10
Classifier: License :: OSI Approved :: MIT License
Classifier: Programming Language :: Python :: 3
Classifier: Programming Language :: Python :: 3.10
Classifier: Programming Language :: Python :: 3.11
Classifier: Programming Language :: Python :: 3.12
Requires-Dist: robotframework (>=5.0.1)
Requires-Dist: robotframework-pabot (>2)
